marksocket.py
marksocket-0.4.dist-info/LICENSE
marksocket-0.4.dist-info/METADATA
marksocket-0.4.dist-info/WHEEL
marksocket-0.4.dist-info/entry_points.txt
marksocket-0.4.dist-info/top_level.txt
marksocket-0.4.dist-info/RECORD
